{
    "tasks": {
        "task0": {
            "id": "task0",
            "objective": "Define core data structures: grid representation (2D array), cell states, tetromino shape definitions, and gem color types.",
            "agent_id": 1,
            "next": [
                "task1",
                "task2",
                "task3",
                "task4"
            ],
            "prev": [],
            "status": "pending",
            "history": "",
            "remaining_dependencies": 0,
            "agent": "research_agent",
            "output_format": "Python code"
        },
        "task1": {
            "id": "task1",
            "objective": "Implement tetromino mechanics: spawn random pieces, handle rotation, lateral movement, gravity-based falling, and lock pieces into the grid.",
            "agent_id": 2,
            "next": [
                "task2",
                "task3",
                "task4"
            ],
            "prev": [
                "task0"
            ],
            "status": "pending",
            "history": "",
            "remaining_dependencies": 1,
            "agent": "coding_agent",
            "output_format": "Python code"
        },
        "task2": {
            "id": "task2",
            "objective": "Develop gem transformation and match logic: convert locked tetromino blocks into colored gems, detect Tetris line clears and Bejeweled match-3 patterns, trigger chain reactions, and update score.",
            "agent_id": 2,
            "next": [
                "task3",
                "task4"
            ],
            "prev": [
                "task0",
                "task1"
            ],
            "status": "pending",
            "history": "",
            "remaining_dependencies": 2,
            "agent": "coding_agent",
            "output_format": "Python code"
        },
        "task3": {
            "id": "task3",
            "objective": "Build the Pygame GUI: render the game grid, animate falling blocks and gem clears, display current score and next tetromino preview.",
            "agent_id": 2,
            "next": [
                "task4"
            ],
            "prev": [
                "task0",
                "task1",
                "task2"
            ],
            "status": "pending",
            "history": "",
            "remaining_dependencies": 3,
            "agent": "coding_agent",
            "output_format": "Python code"
        },
        "task4": {
            "id": "task4",
            "objective": "Integrate keyboard controls and main game loop: capture input (move, rotate, drop), update game state each frame, and call rendering and logic routines.",
            "agent_id": 1,
            "next": [],
            "prev": [
                "task0",
                "task1",
                "task2",
                "task3"
            ],
            "status": "pending",
            "history": "",
            "remaining_dependencies": 4,
            "agent": "research_agent",
            "output_format": "Python code"
        }
    }
}