{
  "description": "Initial execution result for task task3",
  "timestamp": "2026-05-23T10:44:49.944312",
  "task_id": "task3",
  "iteration": 0,
  "data": {
    "task_objective": "Create keyboard control handlers for tetromino movement, rotation, and hard/soft drops",
    "agent_id": 1,
    "context": "Task task1:\n  Objective: Implement tetromino behavior: rotation, horizontal movement, gravity drop, locking into grid and conversion to colored gems\n  Result: ```python\nimport pygame\nimport random\n\n# Define colors\nCOLORS = {\n    \"red\": (255, 0, 0),\n    \"green\": (0, 255, 0),\n    \"blue\": (0, 0, 255),\n    \"yellow\": (255, 255, 0),\n    \"cyan\": (0, 255, 255),\n    \"magenta\": (255, 0, 255),\n    \"orange\": (255, 165, 0),\n    \"gray\": (128, 128, 128)\n}\n\n# Tetromino definitions\nTETROMINOS = {\n    \"I\": {\"shape\": [[1,1,1,1]],             \"color\": \"cyan\"},\n    \"J\": {\"shape\": [[1,0,0],[1,1,1]],       \"color\": \"blue\"},\n    \"L\": {\"shape\": [[0,0,1],[1,1,1]],       \"color\": \"orange\"},\n    \"O\": {\"shape\": [[1,1],[1,1]],           \"color\": \"yellow\"},\n    \"S\": {\"shape\": [[0,1,1],[1,1,0]],       \"color\": \"green\"},\n    \"T\": {\"shape\": [[0,1,0],[1,1,1]],       \"color\": \"magenta\"},\n    \"Z\": {\"shape\": [[1,1,0],[0,1,1]],       \"color\": \"red\"}\n}\n\nGRID_WIDTH  = 10\nGRID_HEIGHT = 20\n\nclass Gem:\n    \"\"\"A single colored gem in the grid.\"\"\"\n    def __init__(self, color_name):\n        self.color_name = color_name\n        self.rgb = COLORS[color_name]\n\nclass Tetromino:\n    def __init__(self, shape, color_name, x=3, y=0):\n        self.shape = [row[:] for row in shape]\n        self.color = color_name\n        self.x = x\n        self.y = y\n\n    def _rotate_shape(self):\n        return [list(row) for row in zip(*self.shape[::-1])]\n\n    def rotate(self, grid):\n        \"\"\"Attempt to rotate; revert if invalid.\"\"\"\n        old_shape = self.shape\n        self.shape = self._rotate_shape()\n        if not is_valid_position(self, grid):\n            self.shape = old_shape\n\n    def move(self, dx, grid):\n        \"\"\"Attempt horizontal move; revert if invalid.\"\"\"\n        old_x = self.x\n        self.x += dx\n        if not is_valid_position(self, grid):\n            self.x = old_x\n\n    def soft_drop(self, grid):\n        \"\"\"Move down one; return False if it would collide.\"\"\"\n        old_y = self.y\n        self.y += 1\n        if not is_valid_position(self, grid):\n            self.y = old_y\n            return False\n        return True\n\n    def hard_drop(self, grid):\n        \"\"\"Drop until collision; lock in place at the end.\"\"\"\n        while self.soft_drop(grid):\n            pass\n        return False  # indicates it landed\n\ndef create_grid(width, height):\n    \"\"\"Initialize empty grid of specified size.\"\"\"\n    return [[None for _ in range(width)] for _ in range(height)]\n\ndef is_valid_position(tetromino, grid):\n    \"\"\"Check if tetromino is within bounds and not colliding.\"\"\"\n    for dy, row in enumerate(tetromino.shape):\n        for dx, cell in enumerate(row):\n            if cell:\n                x = tetromino.x + dx\n                y = tetromino.y + dy\n                if x < 0 or x >= GRID_WIDTH or y < 0 or y >= GRID_HEIGHT:\n                    return False\n                if grid[y][x] is not None:\n                    return False\n    return True\n\ndef lock_tetromino(tetromino, grid):\n    \"\"\"Convert all occupied cells of the tetromino into Gems in the grid.\"\"\"\n    for dy, row in enumerate(tetromino.shape):\n        for dx, cell in enumerate(row):\n            if cell:\n                x = tetromino.x + dx\n                y = tetromino.y + dy\n                if 0 <= x < GRID_WIDTH and 0 <= y < GRID_HEIGHT:\n                    grid[y][x] = Gem(tetromino.color)\n\nclass TetrominoManager:\n    \"\"\"Manages active tetromino, spawning, and locking.\"\"\"\n    def __init__(self, grid):\n        self.grid = grid\n        self.current = self._spawn_new()\n\n    def _spawn_new(self):\n        key = random.choice(list(TETROMINOS.keys()))\n        data = TETROMINOS[key]\n        # center initial x so shape appears roughly in middle\n        start_x = (GRID_WIDTH - len(data[\"shape\"][0])) // 2\n        return Tetromino(data[\"shape\"], data[\"color\"], x=start_x, y=0)\n\n    def update(self, command=None):\n        \"\"\"\n        command: one of 'left','right','rotate','soft_drop','hard_drop'\n        Returns True if piece locked (and a new spawn occurred).\n        \"\"\"\n        if command == 'left':\n            self.current.move(-1, self.grid)\n        elif command == 'right':\n            self.current.move(1, self.grid)\n        elif command == 'rotate':\n            self.current.rotate(self.grid)\n        elif command == 'soft_drop':\n            landed = not self.current.soft_drop(self.grid)\n            if landed:\n                lock_tetromino(self.current, self.grid)\n                self.current = self._spawn_new()\n                return True\n        elif command == 'hard_drop':\n            self.current.hard_drop(self.grid)\n            lock_tetromino(self.current, self.grid)\n            self.current = self._spawn_new()\n            return True\n        else:\n            # gravity tick\n            landed = not self.current.soft_drop(self.grid)\n            if landed:\n                lock_tetromino(self.current, self.grid)\n                self.current = self._spawn_new()\n                return True\n        return False\n```",
    "next_objective": "Task task6:\n  Objective: Assemble main game loop: orchestrate piece spawning, controls input, physics updates, gem conversion, match processing, scoring, and GUI updates",
    "result": "```python\nimport pygame\nimport random\n\n# Define colors\nCOLORS = {\n    \"red\": (255, 0, 0),\n    \"green\": (0, 255, 0),\n    \"blue\": (0, 0, 255),\n    \"yellow\": (255, 255, 0),\n    \"cyan\": (0, 255, 255),\n    \"magenta\": (255, 0, 255),\n    \"orange\": (255, 165, 0),\n    \"gray\": (128, 128, 128)\n}\n\n# Tetromino definitions\nTETROMINOS = {\n    \"I\": {\"shape\": [[1,1,1,1]],             \"color\": \"cyan\"},\n    \"J\": {\"shape\": [[1,0,0],[1,1,1]],       \"color\": \"blue\"},\n    \"L\": {\"shape\": [[0,0,1],[1,1,1]],       \"color\": \"orange\"},\n    \"O\": {\"shape\": [[1,1],[1,1]],           \"color\": \"yellow\"},\n    \"S\": {\"shape\": [[0,1,1],[1,1,0]],       \"color\": \"green\"},\n    \"T\": {\"shape\": [[0,1,0],[1,1,1]],       \"color\": \"magenta\"},\n    \"Z\": {\"shape\": [[1,1,0],[0,1,1]],       \"color\": \"red\"}\n}\n\nGRID_WIDTH  = 10\nGRID_HEIGHT = 20\n\nclass Gem:\n    \"\"\"A single colored gem in the grid.\"\"\"\n    def __init__(self, color_name):\n        self.color_name = color_name\n        self.rgb = COLORS[color_name]\n\nclass Tetromino:\n    def __init__(self, shape, color_name, x=3, y=0):\n        self.shape = [row[:] for row in shape]\n        self.color = color_name\n        self.x = x\n        self.y = y\n\n    def _rotate_shape(self):\n        return [list(row) for row in zip(*self.shape[::-1])]\n\n    def rotate(self, grid):\n        \"\"\"Attempt to rotate; revert if invalid.\"\"\"\n        old_shape = self.shape\n        self.shape = self._rotate_shape()\n        if not is_valid_position(self, grid):\n            self.shape = old_shape\n\n    def move(self, dx, grid):\n        \"\"\"Attempt horizontal move; revert if invalid.\"\"\"\n        old_x = self.x\n        self.x += dx\n        if not is_valid_position(self, grid):\n            self.x = old_x\n\n    def soft_drop(self, grid):\n        \"\"\"Move down one; return False if it would collide.\"\"\"\n        old_y = self.y\n        self.y += 1\n        if not is_valid_position(self, grid):\n            self.y = old_y\n            return False\n        return True\n\n    def hard_drop(self, grid):\n        \"\"\"Drop until collision; lock in place at the end.\"\"\"\n        while self.soft_drop(grid):\n            pass\n        return False  # indicates it landed\n\ndef create_grid(width, height):\n    \"\"\"Initialize empty grid of specified size.\"\"\"\n    return [[None for _ in range(width)] for _ in range(height)]\n\ndef is_valid_position(tetromino, grid):\n    \"\"\"Check if tetromino is within bounds and not colliding.\"\"\"\n    for dy, row in enumerate(tetromino.shape):\n        for dx, cell in enumerate(row):\n            if cell:\n                x = tetromino.x + dx\n                y = tetromino.y + dy\n                if x < 0 or x >= GRID_WIDTH or y < 0 or y >= GRID_HEIGHT:\n                    return False\n                if grid[y][x] is not None:\n                    return False\n    return True\n\ndef lock_tetromino(tetromino, grid):\n    \"\"\"Convert all occupied cells of the tetromino into Gems in the grid.\"\"\"\n    for dy, row in enumerate(tetromino.shape):\n        for dx, cell in enumerate(row):\n            if cell:\n                x = tetromino.x + dx\n                y = tetromino.y + dy\n                if 0 <= x < GRID_WIDTH and 0 <= y < GRID_HEIGHT:\n                    grid[y][x] = Gem(tetromino.color)\n\nclass TetrominoManager:\n    \"\"\"Manages active tetromino, spawning, and locking.\"\"\"\n    def __init__(self, grid):\n        self.grid = grid\n        self.current = self._spawn_new()\n\n    def _spawn_new(self):\n        key = random.choice(list(TETROMINOS.keys()))\n        data = TETROMINOS[key]\n        # center initial x so shape appears roughly in middle\n        start_x = (GRID_WIDTH - len(data[\"shape\"][0])) // 2\n        return Tetromino(data[\"shape\"], data[\"color\"], x=start_x, y=0)\n\n    def update(self, command=None):\n        \"\"\"\n        command: one of 'left','right','rotate','soft_drop','hard_drop'\n        Returns True if piece locked (and a new spawn occurred).\n        \"\"\"\n        if command == 'left':\n            self.current.move(-1, self.grid)\n        elif command == 'right':\n            self.current.move(1, self.grid)\n        elif command == 'rotate':\n            self.current.rotate(self.grid)\n        elif command == 'soft_drop':\n            landed = not self.current.soft_drop(self.grid)\n            if landed:\n                lock_tetromino(self.current, self.grid)\n                self.current = self._spawn_new()\n                return True\n        elif command == 'hard_drop':\n            self.current.hard_drop(self.grid)\n            lock_tetromino(self.current, self.grid)\n            self.current = self._spawn_new()\n            return True\n        else:\n            # gravity tick\n            landed = not self.current.soft_drop(self.grid)\n            if landed:\n                lock_tetromino(self.current, self.grid)\n                self.current = self._spawn_new()\n                return True\n        return False\n\ndef handle_input(event, tetromino_manager):\n    \"\"\"Handles keyboard input for controlling the tetromino.\"\"\"\n    if event.type == pygame.KEYDOWN:\n        if event.key == pygame.K_LEFT:\n            tetromino_manager.update('left')\n        elif event.key == pygame.K_RIGHT:\n            tetromino_manager.update('right')\n        elif event.key == pygame.K_UP:\n            tetromino_manager.update('rotate')\n        elif event.key == pygame.K_DOWN:\n            tetromino_manager.update('soft_drop')\n        elif event.key == pygame.K_SPACE:\n            tetromino_manager.update('hard_drop')\n```",
    "execution_time": 9.118497848510742
  }
}